duanjunjie/__init__.py
duanjunjie/pandas_sql.py
duanjunjie-1.0.0.dist-info/LICENSE
duanjunjie-1.0.0.dist-info/METADATA
duanjunjie-1.0.0.dist-info/WHEEL
duanjunjie-1.0.0.dist-info/top_level.txt
duanjunjie-1.0.0.dist-info/RECORD
