Metadata-Version: 2.1
Name: duanjunjie
Version: 1.0.0
Summary: 自己用的工具包
Home-page: https://gitee.com/junjieduan/pytools/tree/master
Author: junjieduan
Author-email: merch_nerve@163.com
Maintainer: junjieduan
Maintainer-email: merch_nerve@163.com
License: BSD License
Platform: all
Classifier: Development Status :: 4 - Beta
Classifier: Operating System :: OS Independent
Classifier: Intended Audience :: Developers
Classifier: License :: OSI Approved :: BSD License
Classifier: Programming Language :: Python
Classifier: Programming Language :: Python :: Implementation
Classifier: Programming Language :: Python :: 2
Classifier: Programming Language :: Python :: 2.7
Classifier: Programming Language :: Python :: 3
Classifier: Programming Language :: Python :: 3.4
Classifier: Programming Language :: Python :: 3.5
Classifier: Programming Language :: Python :: 3.6
Classifier: Topic :: Software Development :: Libraries
License-File: LICENSE
